g1879/__init__.py
g1879/docx.py
g1879/imgs.py
g1879/paths.py
g1879/time.py
g1879/video.py
g1879/www.py
g1879/xlsx.py
g1879/zip.py
g1879-0.5.2.dist-info/LICENSE
g1879-0.5.2.dist-info/METADATA
g1879-0.5.2.dist-info/WHEEL
g1879-0.5.2.dist-info/top_level.txt
g1879-0.5.2.dist-info/RECORD
