Metadata-Version: 2.1
Name: g1879
Version: 0.5.2
Summary: A personal toolkit.
Home-page: https://gitee.com/g1879/g1879
Author: g1879
Author-email: g1879@qq.com
License: MIT
Keywords: g1879
Platform: UNKNOWN
Classifier: Programming Language :: Python :: 3.8
Classifier: Development Status :: 4 - Beta
Classifier: Topic :: Utilities
Classifier: License :: OSI Approved :: MIT License
Requires-Python: >=3.8
